wsw/__init__.py
wsw/__main__.py
wsw/words.py
wsw-0.1.0.dist-info/LICENSE
wsw-0.1.0.dist-info/METADATA
wsw-0.1.0.dist-info/WHEEL
wsw-0.1.0.dist-info/entry_points.txt
wsw-0.1.0.dist-info/top_level.txt
wsw-0.1.0.dist-info/RECORD
